martenczuk/__init__.py
martenczuk/martenczuk.py
martenczuk-0.1.1.dist-info/LICENSE
martenczuk-0.1.1.dist-info/METADATA
martenczuk-0.1.1.dist-info/WHEEL
martenczuk-0.1.1.dist-info/top_level.txt
martenczuk-0.1.1.dist-info/RECORD
