Metadata-Version: 2.1
Name: martenczuk
Version: 0.1.1
Summary: SQL Server,CSV & JSON Connection Objects and Tools
Home-page: UNKNOWN
Author: Kamil Martenczuk
Author-email: <kamil.martenczuk@gmail.com>
License: UNKNOWN
Keywords: python,sql,csv,json
Platform: UNKNOWN
Classifier: Development Status :: 2 - Pre-Alpha
Classifier: Intended Audience :: Developers
Classifier: Programming Language :: Python :: 3
Classifier: Operating System :: Unix
Classifier: Operating System :: MacOS :: MacOS X
Classifier: Operating System :: Microsoft :: Windows
License-File: LICENSE
Requires-Dist: pypyodbc
Requires-Dist: tqdm
